submission_broker/__init__.py
submission_broker/services/__init__.py
submission_broker/services/biosamples.py
submission_broker/services/biostudies.py
submission_broker/services/ena.py
submission_broker/submission/__init__.py
submission_broker/submission/entity.py
submission_broker/submission/submission.py
submission_broker/validation/__init__.py
submission_broker/validation/base.py
submission_broker-0.2.0.dist-info/LICENSE
submission_broker-0.2.0.dist-info/METADATA
submission_broker-0.2.0.dist-info/WHEEL
submission_broker-0.2.0.dist-info/top_level.txt
submission_broker-0.2.0.dist-info/RECORD
