Metadata-Version: 2.1
Name: submission-broker
Version: 0.2.0
Summary: A library written in Python to handle brokering submission into EBI archives.
Home-page: https://github.com/ebi-ait/submission-broker
License: UNKNOWN
Platform: UNKNOWN
Classifier: Development Status :: 3 - Alpha
Classifier: Programming Language :: Python :: 3
Classifier: Operating System :: OS Independent
Requires-Dist: requests
Requires-Dist: biosamples-client
Requires-Dist: biostudies-client
